shortprint/__init__.py
shortprint/config.py
shortprint/requirements.py
shortprint/shortprint.py
shortprint/utils.py
shortprint/typers/__init__.py
shortprint/typers/dataclasses_typer.py
shortprint/typers/dict_typer.py
shortprint/typers/list_typer.py
shortprint/typers/ndarray_typer.py
shortprint/typers/object_typer.py
shortprint/typers/set_typer.py
shortprint/typers/tuple_typer.py
shortprint-0.0.5.dist-info/METADATA
shortprint-0.0.5.dist-info/WHEEL
shortprint-0.0.5.dist-info/top_level.txt
shortprint-0.0.5.dist-info/RECORD
