Metadata-Version: 2.1
Name: shortprint
Version: 0.0.5
Summary: The module to help you understand your data
Home-page: https://github.com/marcoboucas/shortprint
Author: Marco Boucas
License: UNKNOWN
Platform: UNKNOWN
Classifier: Programming Language :: Python :: 3
Classifier: License :: OSI Approved :: MIT License
Classifier: Operating System :: OS Independent
Requires-Python: >=3.6
